{"zH1tuhIz0VaOyEZWq9zgiA==":"img_5233-5d-2000x1295.jpg","8I2abeFhGnAYsLwHmPARIQ==":"img_5233-5d-85x48.png","675vMOfQhtqoYE8k/caGww==":"img_5224-5d-2000x1333.jpg","xn9VtiEUEUWve1Su89uz/A==":"img_5224-5d-85x48.png","hq/nKsStweILRMC5ykd8Xw==":"dell_logo_blue_rgb-122x122.png","M9EVi+WqfzURNREFHKK/eQ==":"img_events-1080x720.jpg","c41VcV7DFAdHdwXQLNWWnw==":"img_events-1024x576.jpg","Su6RLWbZojkhf0iSt18Plg==":"img_events-85x48.png","LHwtXzBZ67IPEUaIvIeAyw==":"img_vapprove-1080x720.jpg","bpD5kBKu9sqUZkDIvINlsg==":"img_vapprove-1024x576.jpg","kBOo8jzijkcmkNuPUvn1+A==":"img_vapprove-85x48.png","yHkh74XWjH+EwN187AWcXQ==":"img_myguest-1080x720.jpg","YKjfKdYYZQcGyaKuncheAg==":"img_myguest-1024x576.jpg","AFxou4rO1hdQwIEpsXAqbA==":"img_myguest-85x48.png"}